pyadm/__init__.py
pyadm/config.py
pyadm/config_commands.py
pyadm/helper.py
pyadm/main.py
pyadm/elastic/__init__.py
pyadm/elastic/click_commands.py
pyadm/elastic/elastic.py
pyadm/ldapcli/__init__.py
pyadm/ldapcli/click_commands.py
pyadm/ldapcli/group_commands.py
pyadm/ldapcli/ldap.py
pyadm/ldapcli/member_commands.py
pyadm/ldapcli/user_commands.py
pyadm/pvecli/__init__.py
pyadm/pvecli/container_commands.py
pyadm/pvecli/network_commands.py
pyadm/pvecli/node_commands.py
pyadm/pvecli/offline_client.py
pyadm/pvecli/pve.py
pyadm/pvecli/pve_commands.py
pyadm/pvecli/storage_commands.py
pyadm/pvecli/vm_commands.py
pyadm_toolkit-0.2.1.dist-info/licenses/LICENSE
pyadm_toolkit-0.2.1.dist-info/METADATA
pyadm_toolkit-0.2.1.dist-info/WHEEL
pyadm_toolkit-0.2.1.dist-info/entry_points.txt
pyadm_toolkit-0.2.1.dist-info/top_level.txt
pyadm_toolkit-0.2.1.dist-info/zip-safe
pyadm_toolkit-0.2.1.dist-info/RECORD
