Metadata-Version: 2.4
Name: pyadm-toolkit
Version: 0.2.1
Summary: PyADM - Python Admin Toolkit. The swiss army knife for every engineer.
Home-page: https://github.com/okleinschmidt/pyadm
Author: Ole Kleinschmidt
Author-email: Ole Kleinschmidt <ok@datenreisende.org>
License: 
Project-URL: homepage, https://github.com/okleinschmidt/pyadm
Project-URL: bug_tracker, https://github.com/okleinschmidt/pyadm/issues
Keywords: python admin toolkit,pyadm,ldap,activedirectory,directoryserver,elasticsearch,opensearch,proxmox,pve
Classifier: Programming Language :: Python :: 3
Classifier: License :: OSI Approved :: MIT License
Classifier: Operating System :: OS Independent
Requires-Python: >=3.10.8
License-File: LICENSE
Requires-Dist: click
Requires-Dist: ldap3
Requires-Dist: elasticsearch
Requires-Dist: opensearch-py
Requires-Dist: tabulate
Requires-Dist: proxmoxer
Dynamic: license-file
